{"_rejected_tensors_proportion": 0.0, "_rejected_tensor_count": 46177, "_tensor_count": 46177, "_categories_count": 6, "bullet_wake": {"count": 5445, "frequency": 0.0026405754794474, "categories_count": 1, "domain_classes": [{"in_range": [100.0, 100.0], "count": 5444, "frequency": 0.9998163452708907}, {"random": [100.0, 100.0], "count": 1, "values": {"in_range": 0.9999764567392584, "flip": 2.3543260741612713e-05}, "frequency": 0.00018365472910927456}], "parameters": [{"keys": {"affected_channels_pct": [0.0, 10.0]}, "stats": {"max_corrupted_channels": 8, "min_channel_skip": 1, "max_channel_skip": 3}, "conditional_frequency": 1.0, "overall_frequency": 0.11791584555081534, "count": 5445}]}, "full_channels": {"count": 30512, "frequency": 0.2482373414520885, "categories_count": 6, "domain_classes": [{"in_range": [100.0, 100.0], "count": 7906, "frequency": 0.2591111693759832}, {"in_range": [87.5, 100.0], "flip": [0.0, 100], "count": 5225, "frequency": 0.171244100681699}, {"in_range": [87.5, 100.0], "zero": [0.0, 100], "count": 2447, "frequency": 0.08019795490298899}, {"out_of_range": [100.0, 100.0], "count": 479, "frequency": 0.015698741478762455}, {"random": [100.0, 100.0], "count": 14455, "values": {"in_range": 0.9970751055179254, "zero": 0.0013086288354204106, "flip": 5.39112691452889e-05, "out_of_range": 0.0015623543775088748}, "frequency": 0.47374803356056633}], "parameters": [{"keys": {"avg_channel_corruption_pct": [90.0, 100.0], "affected_channels_pct": [90.0, 100.0]}, "stats": {"max_corrupted_channels": 128, "min_channel_skip": 1, "max_channel_skip": 1}, "conditional_frequency": 0.6827149973780807, "overall_frequency": 0.45111202546722395, "count": 20831}, {"keys": {"avg_channel_corruption_pct": [90.0, 100.0], "affected_channels_pct": [0.0, 10.0]}, "stats": {"max_corrupted_channels": 8, "min_channel_skip": 1, "max_channel_skip": 1}, "conditional_frequency": 0.24337965390665967, "overall_frequency": 0.16081599064469324, "count": 7426}, {"keys": {"avg_channel_corruption_pct": [80.0, 90.0], "affected_channels_pct": [0.0, 10.0]}, "stats": {"max_corrupted_channels": 8, "min_channel_skip": 1, "max_channel_skip": 1}, "conditional_frequency": 0.020418196119559518, "overall_frequency": 0.013491565064859129, "count": 623}, {"keys": {"avg_channel_corruption_pct": [50.0, 60.0], "affected_channels_pct": [0.0, 10.0]}, "stats": {"max_corrupted_channels": 8, "min_channel_skip": 1, "max_channel_skip": 1}, "conditional_frequency": 0.018877818563188254, "overall_frequency": 0.012473742339259805, "count": 576}, {"keys": {"avg_channel_corruption_pct": [60.0, 70.0], "affected_channels_pct": [0.0, 10.0]}, "stats": {"max_corrupted_channels": 8, "min_channel_skip": 1, "max_channel_skip": 1}, "conditional_frequency": 0.017960146827477715, "overall_frequency": 0.011867379864434676, "count": 548}, {"keys": {"avg_channel_corruption_pct": [70.0, 80.0], "affected_channels_pct": [0.0, 10.0]}, "stats": {"max_corrupted_channels": 8, "min_channel_skip": 1, "max_channel_skip": 1}, "conditional_frequency": 0.016649187205034086, "overall_frequency": 0.011001147757541633, "count": 508}]}, "single_channel_random": {"count": 2505, "frequency": 1.89039205494835e-05, "categories_count": 5, "domain_classes": [{"in_range": [100.0, 100.0], "count": 2496, "frequency": 0.9964071856287425}, {"random": [100.0, 100.0], "count": 9, "values": {"in_range": 0.9999395940721649, "flip": 5.3694158075601374e-05, "zero": 6.711769759450172e-06}, "frequency": 0.003592814371257485}], "parameters": [{"keys": {"channel_corruption_pct": [20.0, 30.0]}, "stats": {"max_cardinality": 76, "min_value_skip": 1, "max_value_skip": 69}, "conditional_frequency": 0.24271457085828343, "overall_frequency": 0.013166728024774239, "count": 608}, {"keys": {"channel_corruption_pct": [10.0, 20.0]}, "stats": {"max_cardinality": 51, "min_value_skip": 1, "max_value_skip": 75}, "conditional_frequency": 0.24191616766467067, "overall_frequency": 0.013123416419429585, "count": 606}, {"keys": {"channel_corruption_pct": [30.0, 40.0]}, "stats": {"max_cardinality": 102, "min_value_skip": 1, "max_value_skip": 39}, "conditional_frequency": 0.21077844311377245, "overall_frequency": 0.011434263810988153, "count": 528}, {"keys": {"channel_corruption_pct": [0.0, 10.0]}, "stats": {"max_cardinality": 25, "min_value_skip": 1, "max_value_skip": 77}, "conditional_frequency": 0.18722554890219562, "overall_frequency": 0.010156571453320917, "count": 469}, {"keys": {"channel_corruption_pct": [40.0, 50.0]}, "stats": {"max_cardinality": 128, "min_value_skip": 1, "max_value_skip": 34}, "conditional_frequency": 0.11736526946107785, "overall_frequency": 0.006366805985663858, "count": 294}]}, "single": {"count": 4628, "frequency": 0.7490931311545371, "categories_count": 1, "domain_classes": [{"in_range": [100.0, 100.0], "count": 4530, "frequency": 0.9788245462402766}, {"random": [100.0, 100.0], "count": 98, "values": {"in_range": 0.9788245462402766, "out_of_range": 0.020959377700950736, "flip": 0.000216076058772688}, "frequency": 0.021175453759723423}], "parameters": [{"keys": {}, "stats": {}, "conditional_frequency": 1.0, "overall_frequency": 0.10022305476752495, "count": 4628}]}, "same_row": {"count": 113, "frequency": 7.535655541265991e-07, "categories_count": 1, "domain_classes": [{"random": [100.0, 100.0], "count": 113, "values": {"in_range": 1.0}, "frequency": 1.0}], "parameters": [{"keys": {"row_corruption_pct": {"RANDOM": [[20.0, 30.0], [70.0, 80.0], [90.0, 100.0], [10.0, 20.0], [80.0, 90.0], [50.0, 60.0], [60.0, 70.0], [40.0, 50.0], [30.0, 40.0]]}}, "stats": {"max_cardinality": {"RANDOM": [2, 4, 6, 7, 8, 10]}, "min_value_skip": {"RANDOM": [1, 14]}, "max_value_skip": {"RANDOM": [2, 3, 4, 6, 9, 14]}}, "conditional_frequency": 1.0, "overall_frequency": 0.0024471057019728438, "count": 113}]}, "single_block": {"count": 240, "frequency": 9.859704452695458e-07, "categories_count": 1, "domain_classes": [{"random": [100.0, 100.0], "count": 240, "values": {"in_range": 0.9998694005485177, "zero": 0.0001305994514823038}, "frequency": 1.0}], "parameters": [{"keys": {"block_size": {"RANDOM": [64, 16, 32]}, "block_corruption_pct": {"RANDOM": [[70.0, 80.0], [90.0, 100.0], [80.0, 90.0], [50.0, 60.0], [60.0, 70.0]]}}, "stats": {}, "conditional_frequency": 1.0, "overall_frequency": 0.0051973926413582516, "count": 240}]}, "skip_4": {"count": 20, "frequency": 0.000433116053446521, "categories_count": 1, "domain_classes": [{"random": [100.0, 100.0], "count": 20, "values": {"in_range": 1.0}, "frequency": 1.0}], "parameters": [{"keys": {"skip_amount": 4, "unique_channel_indexes": {"RANDOM": [2, 3]}, "indexes_corruption_pct": [90.0, 100.0], "affected_channels_pct": [0.0, 10.0]}, "stats": {"max_corrupted_channels": {"RANDOM": [8, 1]}, "min_channel_skip": 1, "max_channel_skip": 1}, "conditional_frequency": 1.0, "overall_frequency": 0.000433116053446521, "count": 20}]}, "shattered_channel": {"count": 1755, "frequency": 4.787352685734052e-06, "categories_count": 2, "domain_classes": [{"in_range": [100.0, 100.0], "count": 1706, "frequency": 0.972079772079772}, {"random": [100.0, 100.0], "count": 49, "values": {"in_range": 0.9978678585863389, "zero": 0.00042129288414445684, "flip": 3.613799006205273e-05, "out_of_range": 0.0016747105394546017}, "frequency": 0.02792022792022792}], "parameters": [{"keys": {"avg_span_corruption_pct": [90.0, 100.0], "affected_channels_pct": [0.0, 10.0]}, "stats": {"max_corrupted_channels": 8, "min_channel_skip": 1, "max_channel_skip": 1, "min_span_width": 2, "max_span_width": 143}, "conditional_frequency": 0.7692307692307693, "overall_frequency": 0.029235333607640166, "count": 1350}, {"keys": {"avg_span_corruption_pct": {"RANDOM": [[20.0, 30.0], [0.0, 10.0], [70.0, 80.0], [90.0, 100.0], [10.0, 20.0], [80.0, 90.0], [50.0, 60.0], [60.0, 70.0], [40.0, 50.0], [30.0, 40.0]]}, "affected_channels_pct": {"RANDOM": [[0.0, 10.0], [90.0, 100.0]]}}, "stats": {"max_corrupted_channels": {"RANDOM": [8, 128]}, "min_channel_skip": 1, "max_channel_skip": 1, "min_span_width": {"RANDOM": [256, 6, 10, 16, 20, 250, 252, 254]}, "max_span_width": {"RANDOM": [256, 110, 67, 158]}}, "conditional_frequency": 0.23076923076923078, "overall_frequency": 0.00877060008229205, "count": 405}]}, "multi_channel_block": {"count": 959, "frequency": 3.296296503530885e-06, "categories_count": 1, "domain_classes": [{"in_range": [100.0, 100.0], "count": 945, "frequency": 0.9854014598540146}, {"random": [100.0, 100.0], "count": 14, "values": {"in_range": 0.9996630405232062, "zero": 0.0003178140519759993, "flip": 1.9145424817831283e-05}, "frequency": 0.014598540145985401}], "parameters": [{"keys": {"block_size": {"RANDOM": [64, 16, 32]}, "avg_block_corruption_pct": {"RANDOM": [[70.0, 80.0], [90.0, 100.0], [80.0, 90.0], [50.0, 60.0], [60.0, 70.0]]}, "affected_channels_pct": [0.0, 10.0]}, "stats": {"max_corrupted_channels": 8, "min_channel_skip": 1, "max_channel_skip": 1}, "conditional_frequency": 1.0, "overall_frequency": 0.020767914762760683, "count": 959}]}}