{"_rejected_tensors_proportion": 0.0002874389192296656, "_rejected_tensor_count": 10437, "_tensor_count": 10434, "_categories_count": 8, "full_channels": {"count": 5272, "frequency": 0.6997218227144739, "categories_count": 6, "domain_classes": [{"in_range": [100.0, 100.0], "count": 4634, "frequency": 0.8789833080424886}, {"out_of_range": [100.0, 100.0], "count": 292, "frequency": 0.05538694992412747}, {"in_range": [87.5, 100.0], "zero": [0.0, 100], "count": 168, "frequency": 0.03186646433990895}, {"random": [100.0, 100.0], "count": 178, "values": {"in_range": 0.7690782134078857, "flip": 4.844724361852018e-05, "zero": 0.1836941689964309, "out_of_range": 0.047179170352064786}, "frequency": 0.03376327769347496}], "parameters": [{"keys": {"avg_channel_corruption_pct": [90.0, 100.0], "affected_channels_pct": [0.0, 10.0]}, "stats": {"max_corrupted_channels": 16, "min_channel_skip": 1, "max_channel_skip": 2}, "conditional_frequency": 0.7477238239757208, "overall_frequency": 0.37780333525014376, "count": 3942}, {"keys": {"avg_channel_corruption_pct": [70.0, 80.0], "affected_channels_pct": [0.0, 10.0]}, "stats": {"max_corrupted_channels": 16, "min_channel_skip": 1, "max_channel_skip": 2}, "conditional_frequency": 0.1430197268588771, "overall_frequency": 0.07226375311481695, "count": 754}, {"keys": {"avg_channel_corruption_pct": [60.0, 70.0], "affected_channels_pct": [0.0, 10.0]}, "stats": {"max_corrupted_channels": 16, "min_channel_skip": 1, "max_channel_skip": 2}, "conditional_frequency": 0.041350531107739, "overall_frequency": 0.020893233659191105, "count": 218}, {"keys": {"avg_channel_corruption_pct": [50.0, 60.0], "affected_channels_pct": [0.0, 10.0]}, "stats": {"max_corrupted_channels": 16, "min_channel_skip": 1, "max_channel_skip": 2}, "conditional_frequency": 0.039264036418816387, "overall_frequency": 0.019838987924094307, "count": 207}, {"keys": {"avg_channel_corruption_pct": [80.0, 90.0], "affected_channels_pct": [0.0, 10.0]}, "stats": {"max_corrupted_channels": 16, "min_channel_skip": 1, "max_channel_skip": 2}, "conditional_frequency": 0.0204855842185129, "overall_frequency": 0.010350776308223116, "count": 108}, {"keys": {"avg_channel_corruption_pct": [90.0, 100.0], "affected_channels_pct": [90.0, 100.0]}, "stats": {"max_corrupted_channels": 384, "min_channel_skip": 1, "max_channel_skip": 1}, "conditional_frequency": 0.008156297420333839, "overall_frequency": 0.004121142419014759, "count": 43}]}, "shattered_channel": {"count": 1673, "frequency": 0.0970044837632127, "categories_count": 6, "domain_classes": [{"in_range": [100.0, 100.0], "count": 1648, "frequency": 0.9850567842199641}, {"random": [100.0, 100.0], "count": 25, "values": {"in_range": 0.9947132713055765, "out_of_range": 0.005208894636634695, "flip": 5.3885116930703737e-05, "zero": 2.3948940858090552e-05}, "frequency": 0.014943215780035863}], "parameters": [{"keys": {"avg_span_corruption_pct": [90.0, 100.0], "affected_channels_pct": [0.0, 10.0]}, "stats": {"max_corrupted_channels": 16, "min_channel_skip": 1, "max_channel_skip": 3, "min_span_width": 2, "max_span_width": 25}, "conditional_frequency": 0.387925881649731, "overall_frequency": 0.062200498370711135, "count": 649}, {"keys": {"avg_span_corruption_pct": [20.0, 30.0], "affected_channels_pct": [0.0, 10.0]}, "stats": {"max_corrupted_channels": 16, "min_channel_skip": 1, "max_channel_skip": 2, "min_span_width": 10, "max_span_width": 25}, "conditional_frequency": 0.11715481171548117, "overall_frequency": 0.01878474218899751, "count": 196}, {"keys": {"avg_span_corruption_pct": [50.0, 60.0], "affected_channels_pct": [0.0, 10.0]}, "stats": {"max_corrupted_channels": 16, "min_channel_skip": 1, "max_channel_skip": 2, "min_span_width": 4, "max_span_width": 25}, "conditional_frequency": 0.10280932456664674, "overall_frequency": 0.016484569676059036, "count": 172}, {"keys": {"avg_span_corruption_pct": [40.0, 50.0], "affected_channels_pct": [0.0, 10.0]}, "stats": {"max_corrupted_channels": 16, "min_channel_skip": 1, "max_channel_skip": 2, "min_span_width": 4, "max_span_width": 25}, "conditional_frequency": 0.09922295277943813, "overall_frequency": 0.01590952654782442, "count": 166}, {"keys": {"avg_span_corruption_pct": [70.0, 80.0], "affected_channels_pct": [0.0, 10.0]}, "stats": {"max_corrupted_channels": 16, "min_channel_skip": 1, "max_channel_skip": 2, "min_span_width": 3, "max_span_width": 25}, "conditional_frequency": 0.09623430962343096, "overall_frequency": 0.01543032394096224, "count": 161}, {"keys": {"avg_span_corruption_pct": {"RANDOM": [[0.0, 10.0], [10.0, 20.0], [80.0, 90.0], [60.0, 70.0], [30.0, 40.0]]}, "affected_channels_pct": [0.0, 10.0]}, "stats": {"max_corrupted_channels": 16, "min_channel_skip": 1, "max_channel_skip": {"RANDOM": [2, 3]}, "min_span_width": {"RANDOM": [3, 4, 6, 10, 20]}, "max_span_width": {"RANDOM": [25, 23]}}, "conditional_frequency": 0.19665271966527198, "overall_frequency": 0.03153153153153153, "count": 329}]}, "rectangles": {"count": 202, "frequency": 0.0398106591022519, "categories_count": 2, "domain_classes": [{"in_range": [100.0, 100.0], "count": 197, "frequency": 0.9752475247524752}, {"random": [100.0, 100.0], "count": 5, "values": {"in_range": 0.985343284590186, "flip": 3.377123366316571e-05, "out_of_range": 0.014622944176150754}, "frequency": 0.024752475247524754}], "parameters": [{"keys": {"rectangle_width": 2, "rectangle_height": 2, "affected_channels_pct": [0.0, 10.0]}, "stats": {"max_corrupted_channels": 16, "min_channel_skip": 1, "max_channel_skip": 2}, "conditional_frequency": 0.7277227722772277, "overall_frequency": 0.01408855664174813, "count": 147}, {"keys": {"rectangle_width": {"RANDOM": [2, 3]}, "rectangle_height": {"RANDOM": [2, 3, 4]}, "affected_channels_pct": [0.0, 10.0]}, "stats": {"max_corrupted_channels": 16, "min_channel_skip": 1, "max_channel_skip": {"RANDOM": [1, 2]}}, "conditional_frequency": 0.2722772277227723, "overall_frequency": 0.0052712286754839945, "count": 55}]}, "multi_channel_block": {"count": 258, "frequency": 1.5666073171881054e-06, "categories_count": 1, "domain_classes": [{"in_range": [100.0, 100.0], "count": 255, "frequency": 0.9883720930232558}, {"random": [100.0, 100.0], "count": 3, "values": {"in_range": 0.9999442927970587, "out_of_range": 3.7138135294226874e-05, "flip": 1.8569067647113437e-05}, "frequency": 0.011627906976744186}], "parameters": [{"keys": {"block_size": 16, "avg_block_corruption_pct": {"RANDOM": [[80.0, 90.0], [60.0, 70.0], [90.0, 100.0], [70.0, 80.0]]}, "affected_channels_pct": [0.0, 10.0]}, "stats": {"max_corrupted_channels": 16, "min_channel_skip": 1, "max_channel_skip": {"RANDOM": [2, 3]}}, "conditional_frequency": 1.0, "overall_frequency": 0.024726854514088556, "count": 258}]}, "single": {"count": 1715, "frequency": 0.1376520177535576, "categories_count": 1, "domain_classes": [{"in_range": [100.0, 100.0], "count": 1594, "frequency": 0.9294460641399417}, {"out_of_range": [100.0, 100.0], "count": 121, "frequency": 0.07055393586005831}], "parameters": [{"keys": {}, "stats": {}, "conditional_frequency": 1.0, "overall_frequency": 0.1643664941537282, "count": 1715}]}, "bullet_wake": {"count": 538, "frequency": 2.1475447059485372e-05, "categories_count": 1, "domain_classes": [{"in_range": [100.0, 100.0], "count": 480, "frequency": 0.8921933085501859}, {"random": [100.0, 100.0], "count": 58, "values": {"out_of_range": 0.10242041254322165, "in_range": 0.8975795874567783}, "frequency": 0.10780669144981413}], "parameters": [{"keys": {"affected_channels_pct": [0.0, 10.0]}, "stats": {"max_corrupted_channels": 16, "min_channel_skip": 1, "max_channel_skip": 3}, "conditional_frequency": 1.0, "overall_frequency": 0.05156220049837071, "count": 538}]}, "single_channel_random": {"count": 497, "frequency": 0.0086353586039173, "categories_count": 4, "domain_classes": [{"in_range": [100.0, 100.0], "count": 462, "frequency": 0.9295774647887324}, {"random": [100.0, 100.0], "count": 35, "values": {"in_range": 0.9271886737937013, "flip": 0.0002889338341519792, "out_of_range": 0.07252239237214678}, "frequency": 0.07042253521126761}], "parameters": [{"keys": {"channel_corruption_pct": [30.0, 40.0]}, "stats": {"max_cardinality": 10, "min_value_skip": 1, "max_value_skip": 16}, "conditional_frequency": 0.2917505030181087, "overall_frequency": 0.013896875599003258, "count": 145}, {"keys": {"channel_corruption_pct": [20.0, 30.0]}, "stats": {"max_cardinality": 7, "min_value_skip": 1, "max_value_skip": 17}, "conditional_frequency": 0.28772635814889336, "overall_frequency": 0.013705194556258385, "count": 143}, {"keys": {"channel_corruption_pct": [10.0, 20.0]}, "stats": {"max_cardinality": 5, "min_value_skip": 1, "max_value_skip": 20}, "conditional_frequency": 0.24748490945674045, "overall_frequency": 0.011788384128809662, "count": 123}, {"keys": {"channel_corruption_pct": {"RANDOM": [[40.0, 50.0], [0.0, 10.0]]}}, "stats": {"max_cardinality": {"RANDOM": [2, 12]}, "min_value_skip": {"RANDOM": [1, 2]}, "max_value_skip": {"RANDOM": [13, 23]}}, "conditional_frequency": 0.17303822937625754, "overall_frequency": 0.008242284838029518, "count": 86}]}, "same_row": {"count": 127, "frequency": 0.0021962431725604, "categories_count": 1, "domain_classes": [{"in_range": [100.0, 100.0], "count": 124, "frequency": 0.9538461538461539}, {"random": [100.0, 100.0], "count": 6, "values": {"in_range": 0.9571045576407506, "out_of_range": 0.04289544235924933}, "frequency": 0.046153846153846156}], "parameters": [{"keys": {"row_corruption_pct": [90.0, 100.0]}, "stats": {"max_cardinality": 5, "min_value_skip": 1, "max_value_skip": 2}, "conditional_frequency": 1.0, "overall_frequency": 0.012171746214299405, "count": 127}]}, "single_block": {"count": 56, "frequency": 0.0002932538821028, "categories_count": 1, "domain_classes": [{"random": [100.0, 100.0], "count": 56, "values": {"in_range": 0.9823788546255506, "out_of_range": 0.01762114537444934}, "frequency": 1.0}], "parameters": [{"keys": {"block_size": 16, "block_corruption_pct": {"RANDOM": [[80.0, 90.0], [60.0, 70.0], [90.0, 100.0], [70.0, 80.0]]}}, "stats": {}, "conditional_frequency": 1.0, "overall_frequency": 0.005367069196856431, "count": 56}]}, "skip_4": {"count": 33, "frequency": 0.0031627372052903968, "categories_count": 1, "domain_classes": [{"random": [100.0, 100.0], "count": 33, "values": {"in_range": 0.997624703087886, "out_of_range": 0.0023752969121140144}, "frequency": 1.0}], "parameters": [{"keys": {"skip_amount": 4, "unique_channel_indexes": {"RANDOM": [2, 3]}, "indexes_corruption_pct": [90.0, 100.0], "affected_channels_pct": [0.0, 10.0]}, "stats": {"max_corrupted_channels": {"RANDOM": [16, 14]}, "min_channel_skip": 1, "max_channel_skip": {"RANDOM": [1, 2]}}, "conditional_frequency": 1.0, "overall_frequency": 0.0031627372052903968, "count": 33}]}, "quasi_shattered_channel": {"count": 63, "frequency": 0.0143700933460622, "categories_count": 1, "domain_classes": [{"random": [100.0, 100.0], "count": 63, "values": {"in_range": 1.0}, "frequency": 1.0}], "parameters": [{"keys": {"avg_span_corruption_pct": {"RANDOM": [[20.0, 30.0], [70.0, 80.0], [90.0, 100.0], [80.0, 90.0], [50.0, 60.0], [60.0, 70.0], [40.0, 50.0], [30.0, 40.0]]}, "affected_channels_pct": [0.0, 10.0]}, "stats": {"max_corrupted_channels": 16, "min_channel_skip": 1, "max_channel_skip": {"RANDOM": [1, 2]}, "min_span_width": {"RANDOM": [1, 2, 3, 6, 11]}, "max_span_width": {"RANDOM": [4, 8, 15, 16, 17, 18, 25]}}, "conditional_frequency": 1.0, "overall_frequency": 0.0060379528464634845, "count": 63}]}}