{"_rejected_tensors_proportion": 0.0, "_rejected_tensor_count": 26521, "_tensor_count": 26521, "_categories_count": 10, "full_channels": {"count": 13783, "frequency": 0.0355995001300101, "categories_count": 10, "domain_classes": [{"in_range": [100.0, 100.0], "count": 12570, "frequency": 0.9119930348980628}, {"out_of_range": [100.0, 100.0], "count": 1004, "frequency": 0.07284335775955887}, {"random": [100.0, 100.0], "count": 209, "values": {"in_range": 0.907493925745628, "out_of_range": 0.08498201083366369, "flip": 9.07596615381954e-07, "zero": 0.007523155824092861}, "frequency": 0.015163607342378291}], "parameters": [{"keys": {"avg_channel_corruption_pct": [90.0, 100.0], "affected_channels_pct": [20.0, 30.0]}, "stats": {"max_corrupted_channels": 32, "min_channel_skip": 1, "max_channel_skip": 1}, "conditional_frequency": 0.6841036058913154, "overall_frequency": 0.35552958033256665, "count": 9429}, {"keys": {"avg_channel_corruption_pct": [80.0, 90.0], "affected_channels_pct": [20.0, 30.0]}, "stats": {"max_corrupted_channels": 32, "min_channel_skip": 1, "max_channel_skip": 1}, "conditional_frequency": 0.0720452731625916, "overall_frequency": 0.03744202707288564, "count": 993}, {"keys": {"avg_channel_corruption_pct": [60.0, 70.0], "affected_channels_pct": [20.0, 30.0]}, "stats": {"max_corrupted_channels": 32, "min_channel_skip": 1, "max_channel_skip": 1}, "conditional_frequency": 0.036929550896031345, "overall_frequency": 0.01919233814712869, "count": 509}, {"keys": {"avg_channel_corruption_pct": [50.0, 60.0], "affected_channels_pct": [0.0, 10.0]}, "stats": {"max_corrupted_channels": 1, "min_channel_skip": 1, "max_channel_skip": 1}, "conditional_frequency": 0.033809765653341074, "overall_frequency": 0.01757098148636929, "count": 466}, {"keys": {"avg_channel_corruption_pct": [60.0, 70.0], "affected_channels_pct": [0.0, 10.0]}, "stats": {"max_corrupted_channels": 1, "min_channel_skip": 1, "max_channel_skip": 1}, "conditional_frequency": 0.03373721250816223, "overall_frequency": 0.01753327551751442, "count": 465}, {"keys": {"avg_channel_corruption_pct": [70.0, 80.0], "affected_channels_pct": [20.0, 30.0]}, "stats": {"max_corrupted_channels": 32, "min_channel_skip": 1, "max_channel_skip": 1}, "conditional_frequency": 0.03279402162083726, "overall_frequency": 0.017043097922401117, "count": 452}, {"keys": {"avg_channel_corruption_pct": [80.0, 90.0], "affected_channels_pct": [0.0, 10.0]}, "stats": {"max_corrupted_channels": 10, "min_channel_skip": 1, "max_channel_skip": 1}, "conditional_frequency": 0.02923891750707393, "overall_frequency": 0.0151955054485125, "count": 403}, {"keys": {"avg_channel_corruption_pct": [50.0, 60.0], "affected_channels_pct": [20.0, 30.0]}, "stats": {"max_corrupted_channels": 32, "min_channel_skip": 1, "max_channel_skip": 1}, "conditional_frequency": 0.029021258071537402, "overall_frequency": 0.01508238754194789, "count": 400}, {"keys": {"avg_channel_corruption_pct": [70.0, 80.0], "affected_channels_pct": [0.0, 10.0]}, "stats": {"max_corrupted_channels": 1, "min_channel_skip": 1, "max_channel_skip": 1}, "conditional_frequency": 0.02713487629688747, "overall_frequency": 0.014102032351721278, "count": 374}, {"keys": {"avg_channel_corruption_pct": {"RANDOM": [[80.0, 90.0], [90.0, 100.0]]}, "affected_channels_pct": {"RANDOM": [[0.0, 10.0], [90.0, 100.0], [10.0, 20.0]]}}, "stats": {"max_corrupted_channels": {"RANDOM": [128, 1, 24]}, "min_channel_skip": 1, "max_channel_skip": 1}, "conditional_frequency": 0.021185518392222304, "overall_frequency": 0.01101014290562196, "count": 292}]}, "shattered_channel": {"count": 2062, "frequency": 0.0340128318406669, "categories_count": 2, "domain_classes": [{"in_range": [100.0, 100.0], "count": 2021, "frequency": 0.9801163918525703}, {"random": [100.0, 100.0], "count": 41, "values": {"in_range": 0.9894716966046385, "out_of_range": 0.010526543398137269, "flip": 1.7599972242329493e-06}, "frequency": 0.01988360814742968}], "parameters": [{"keys": {"avg_span_corruption_pct": [90.0, 100.0], "affected_channels_pct": [20.0, 30.0]}, "stats": {"max_corrupted_channels": 32, "min_channel_skip": 1, "max_channel_skip": 2, "min_span_width": 2, "max_span_width": 148}, "conditional_frequency": 0.7429679922405431, "overall_frequency": 0.05776554428566042, "count": 1532}, {"keys": {"avg_span_corruption_pct": {"RANDOM": [[20.0, 30.0], [0.0, 10.0], [70.0, 80.0], [90.0, 100.0], [10.0, 20.0], [80.0, 90.0], [50.0, 60.0], [40.0, 50.0], [30.0, 40.0]]}, "affected_channels_pct": {"RANDOM": [[20.0, 30.0], [0.0, 10.0]]}}, "stats": {"max_corrupted_channels": {"RANDOM": [32, 2, 3, 4, 5]}, "min_channel_skip": {"RANDOM": [1, 10, 2, 6]}, "max_channel_skip": {"RANDOM": [1, 2, 10, 14, 22]}, "min_span_width": {"RANDOM": [33, 97, 1, 7, 11, 239, 16, 17, 18, 19]}, "max_span_width": {"RANDOM": [256, 3, 7, 11, 17, 18, 19]}}, "conditional_frequency": 0.25703200775945684, "overall_frequency": 0.019984163493080954, "count": 530}]}, "rectangles": {"count": 1271, "frequency": 0.0648379602487594, "categories_count": 2, "domain_classes": [{"in_range": [100.0, 100.0], "count": 1230, "frequency": 0.967741935483871}, {"random": [100.0, 100.0], "count": 41, "values": {"in_range": 0.9835626239356567, "out_of_range": 0.01643583409660736, "flip": 1.5419677358670947e-06}, "frequency": 0.03225806451612903}], "parameters": [{"keys": {"rectangle_width": 2, "rectangle_height": 2, "affected_channels_pct": [20.0, 30.0]}, "stats": {"max_corrupted_channels": 32, "min_channel_skip": 1, "max_channel_skip": 4}, "conditional_frequency": 0.7686860739575138, "overall_frequency": 0.03683873157120772, "count": 977}, {"keys": {"rectangle_width": {"RANDOM": [2, 3, 14]}, "rectangle_height": {"RANDOM": [2, 4, 5, 6, 7, 8]}, "affected_channels_pct": {"RANDOM": [[20.0, 30.0], [0.0, 10.0], [10.0, 20.0]]}}, "stats": {"max_corrupted_channels": {"RANDOM": [32, 1, 12, 15]}, "min_channel_skip": 1, "max_channel_skip": {"RANDOM": [8, 1, 20]}}, "conditional_frequency": 0.23131392604248624, "overall_frequency": 0.011085554843331699, "count": 294}]}, "multi_channel_block": {"count": 1253, "frequency": 2.134930444883717e-06, "categories_count": 2, "domain_classes": [{"in_range": [100.0, 100.0], "count": 1240, "frequency": 0.9896249002394254}, {"random": [100.0, 100.0], "count": 13, "values": {"in_range": 0.9901750467905809, "flip": 2.565038693608693e-06, "out_of_range": 0.009822388170725555}, "frequency": 0.010375099760574621}], "parameters": [{"keys": {"block_size": 16, "avg_block_corruption_pct": [90.0, 100.0], "affected_channels_pct": [20.0, 30.0]}, "stats": {"max_corrupted_channels": 32, "min_channel_skip": 1, "max_channel_skip": 1}, "conditional_frequency": 0.2346368715083799, "overall_frequency": 0.011085554843331699, "count": 294}, {"keys": {"block_size": {"RANDOM": [64, 16, 32]}, "avg_block_corruption_pct": {"RANDOM": [[70.0, 80.0], [90.0, 100.0], [80.0, 90.0], [50.0, 60.0], [60.0, 70.0], [40.0, 50.0], [30.0, 40.0]]}, "affected_channels_pct": [20.0, 30.0]}, "stats": {"max_corrupted_channels": 32, "min_channel_skip": 1, "max_channel_skip": 1}, "conditional_frequency": 0.7653631284916201, "overall_frequency": 0.03616002413182007, "count": 959}]}, "single": {"count": 2628, "frequency": 0.7875474943904576, "categories_count": 1, "domain_classes": [{"in_range": [100.0, 100.0], "count": 2623, "frequency": 0.9980974124809742}, {"random": [100.0, 100.0], "count": 5, "values": {"in_range": 0.9980974124809742, "out_of_range": 0.001902587519025875}, "frequency": 0.001902587519025875}], "parameters": [{"keys": {}, "stats": {}, "conditional_frequency": 1.0, "overall_frequency": 0.09909128615059765, "count": 2628}]}, "single_channel_random": {"count": 2222, "frequency": 0.0199175188747942, "categories_count": 5, "domain_classes": [{"in_range": [100.0, 100.0], "count": 2218, "frequency": 0.9981998199819982}, {"random": [100.0, 100.0], "count": 4, "values": {"in_range": 0.999971052041193, "flip": 2.1710969105290964e-05, "out_of_range": 7.2369897017636546e-06}, "frequency": 0.0018001800180018}], "parameters": [{"keys": {"channel_corruption_pct": [0.0, 10.0]}, "stats": {"max_cardinality": 25, "min_value_skip": 1, "max_value_skip": 166}, "conditional_frequency": 0.23852385238523852, "overall_frequency": 0.019984163493080954, "count": 530}, {"keys": {"channel_corruption_pct": [40.0, 50.0]}, "stats": {"max_cardinality": 128, "min_value_skip": 1, "max_value_skip": 64}, "conditional_frequency": 0.1998199819981998, "overall_frequency": 0.01674145017156216, "count": 444}, {"keys": {"channel_corruption_pct": [10.0, 20.0]}, "stats": {"max_cardinality": 51, "min_value_skip": 1, "max_value_skip": 146}, "conditional_frequency": 0.18991899189918993, "overall_frequency": 0.015911918856755025, "count": 422}, {"keys": {"channel_corruption_pct": [20.0, 30.0]}, "stats": {"max_cardinality": 76, "min_value_skip": 1, "max_value_skip": 100}, "conditional_frequency": 0.18901890189018902, "overall_frequency": 0.015836506919045285, "count": 420}, {"keys": {"channel_corruption_pct": [30.0, 40.0]}, "stats": {"max_cardinality": 102, "min_value_skip": 1, "max_value_skip": 72}, "conditional_frequency": 0.18271827182718273, "overall_frequency": 0.015308623355077109, "count": 406}]}, "bullet_wake": {"count": 2262, "frequency": 0.0086088465832432, "categories_count": 2, "domain_classes": [{"in_range": [100.0, 100.0], "count": 2153, "frequency": 0.9518125552608311}, {"random": [100.0, 100.0], "count": 109, "values": {"out_of_range": 0.038374043847925615, "in_range": 0.9616259561520744}, "frequency": 0.048187444739168875}], "parameters": [{"keys": {"affected_channels_pct": [20.0, 30.0]}, "stats": {"max_corrupted_channels": 32, "min_channel_skip": 1, "max_channel_skip": 4}, "conditional_frequency": 0.9770114942528736, "overall_frequency": 0.08333019116926209, "count": 2210}, {"keys": {"affected_channels_pct": {"RANDOM": [[0.0, 10.0], [10.0, 20.0]]}}, "stats": {"max_corrupted_channels": {"RANDOM": [25, 12]}, "min_channel_skip": 1, "max_channel_skip": {"RANDOM": [26, 6]}}, "conditional_frequency": 0.022988505747126436, "overall_frequency": 0.001960710380453226, "count": 52}]}, "single_block": {"count": 234, "frequency": 2.6930267872140368e-05, "categories_count": 1, "domain_classes": [{"random": [100.0, 100.0], "count": 234, "values": {"in_range": 1.0}, "frequency": 1.0}], "parameters": [{"keys": {"block_size": {"RANDOM": [64, 16, 32]}, "block_corruption_pct": {"RANDOM": [[70.0, 80.0], [90.0, 100.0], [80.0, 90.0], [50.0, 60.0], [60.0, 70.0]]}}, "stats": {}, "conditional_frequency": 1.0, "overall_frequency": 0.008823196712039516, "count": 234}]}, "same_row": {"count": 108, "frequency": 0.0010802537454984, "categories_count": 1, "domain_classes": [{"random": [100.0, 100.0], "count": 108, "values": {"in_range": 1.0}, "frequency": 1.0}], "parameters": [{"keys": {"row_corruption_pct": {"RANDOM": [[20.0, 30.0], [70.0, 80.0], [90.0, 100.0], [80.0, 90.0], [50.0, 60.0], [60.0, 70.0], [40.0, 50.0], [30.0, 40.0]]}}, "stats": {"max_cardinality": {"RANDOM": [3, 4, 6, 8, 10]}, "min_value_skip": 1, "max_value_skip": {"RANDOM": [3, 4, 5, 6, 11, 13]}}, "conditional_frequency": 1.0, "overall_frequency": 0.00407224463632593, "count": 108}]}, "skip_4": {"count": 412, "frequency": 0.015534859168206327, "categories_count": 1, "domain_classes": [{"in_range": [100.0, 100.0], "count": 412, "frequency": 1.0}], "parameters": [{"keys": {"skip_amount": 4, "unique_channel_indexes": {"RANDOM": [2, 3, 4, 5, 6, 7, 8, 9, 10, 12, 13, 14, 15, 16]}, "indexes_corruption_pct": [90.0, 100.0], "affected_channels_pct": {"RANDOM": [[20.0, 30.0], [0.0, 10.0]]}}, "stats": {"max_corrupted_channels": {"RANDOM": [32, 1, 4]}, "min_channel_skip": 1, "max_channel_skip": {"RANDOM": [1, 20]}}, "conditional_frequency": 1.0, "overall_frequency": 0.015534859168206327, "count": 412}]}, "quasi_shattered_channel": {"count": 269, "frequency": 0.0425131748507192, "categories_count": 1, "domain_classes": [{"in_range": [100.0, 100.0], "count": 268, "frequency": 0.9962825278810409}, {"random": [100.0, 100.0], "count": 1, "values": {"in_range": 0.9999547879555113, "out_of_range": 4.5212044488651776e-05}, "frequency": 0.0037174721189591076}], "parameters": [{"keys": {"avg_span_corruption_pct": {"RANDOM": [[20.0, 30.0], [0.0, 10.0], [90.0, 100.0], [10.0, 20.0], [80.0, 90.0], [40.0, 50.0], [30.0, 40.0]]}, "affected_channels_pct": {"RANDOM": [[20.0, 30.0], [0.0, 10.0], [10.0, 20.0]]}}, "stats": {"max_corrupted_channels": {"RANDOM": [32, 3, 4, 5, 8, 10, 12, 19, 25]}, "min_channel_skip": {"RANDOM": [1, 2, 11]}, "max_channel_skip": {"RANDOM": [1, 2, 3, 4, 5, 6, 11, 14, 16, 18, 20, 25]}, "min_span_width": {"RANDOM": [1, 17, 239]}, "max_span_width": {"RANDOM": [33, 34, 3, 6, 240, 18, 19]}}, "conditional_frequency": 1.0, "overall_frequency": 0.010142905621959956, "count": 269}]}, "multiple_channels_uncategorized": {"count": 17, "frequency": 0.0021256855679097, "categories_count": 1, "domain_classes": [{"random": [100.0, 100.0], "count": 17, "values": {"in_range": 1.0}, "frequency": 1.0}], "parameters": [{"keys": {"avg_channel_corruption_pct": [0.0, 10.0], "affected_channels_pct": [0.0, 10.0]}, "stats": {"max_corrupted_channels": 4, "min_errors_per_channel": 1, "max_errors_per_channel": 3, "min_channel_skip": 2, "max_channel_skip": 20}, "conditional_frequency": 1.0, "overall_frequency": 0.0006410014705327854, "count": 17}]}}