{"_rejected_tensors_proportion": 0.0, "_tensor_count": 27850, "_categories_count": 7, "multi_channel_block": {"count": 13474, "frequency": 0.0107986109471474, "categories_count": 6, "domain_classes": [{"in_range": [100.0, 100.0], "count": 10886, "frequency": 0.8079263767255455}, {"in_range": [87.5, 100.0], "flip": [0.0, 100], "count": 1239, "frequency": 0.0919548760575924}, {"in_range": [87.5, 100.0], "zero": [0.0, 100], "count": 761, "frequency": 0.05647914502003859}, {"random": [100.0, 100.0], "count": 588, "values": {"in_range": 0.9204285086406524, "zero": 0.061557903322311994, "flip": 0.00021117683966005764, "out_of_range": 0.01780241119737559}, "frequency": 0.043639602196823515}], "parameters": [{"keys": {"block_size": 64, "avg_block_corruption_pct": [90.0, 100.0], "affected_channels_pct": [0.0, 10.0]}, "stats": {"max_corrupted_channels": 16, "min_channel_skip": 1, "max_channel_skip": 241}, "conditional_frequency": 0.7447677007570135, "overall_frequency": 0.36032315978456014, "count": 10035}, {"keys": {"block_size": 64, "avg_block_corruption_pct": [80.0, 90.0], "affected_channels_pct": [0.0, 10.0]}, "stats": {"max_corrupted_channels": 8, "min_channel_skip": 1, "max_channel_skip": 2}, "conditional_frequency": 0.08223244767700758, "overall_frequency": 0.03978456014362657, "count": 1108}, {"keys": {"block_size": 64, "avg_block_corruption_pct": [70.0, 80.0], "affected_channels_pct": [0.0, 10.0]}, "stats": {"max_corrupted_channels": 8, "min_channel_skip": 1, "max_channel_skip": 2}, "conditional_frequency": 0.04007718569096037, "overall_frequency": 0.01938958707360862, "count": 540}, {"keys": {"block_size": 64, "avg_block_corruption_pct": [60.0, 70.0], "affected_channels_pct": [0.0, 10.0]}, "stats": {"max_corrupted_channels": 8, "min_channel_skip": 1, "max_channel_skip": 2}, "conditional_frequency": 0.03332343773192816, "overall_frequency": 0.016122082585278277, "count": 449}, {"keys": {"block_size": 64, "avg_block_corruption_pct": [50.0, 60.0], "affected_channels_pct": [0.0, 10.0]}, "stats": {"max_corrupted_channels": 8, "min_channel_skip": 1, "max_channel_skip": 3}, "conditional_frequency": 0.03183909752115185, "overall_frequency": 0.01540394973070018, "count": 429}, {"keys": {"block_size": {"RANDOM": [32, 16, 64]}, "avg_block_corruption_pct": {"RANDOM": [[70.0, 80.0], [90.0, 100.0], [80.0, 90.0], [50.0, 60.0], [60.0, 70.0], [40.0, 50.0]]}, "affected_channels_pct": {"RANDOM": [[0.0, 10.0], [90.0, 100.0]]}}, "stats": {"max_corrupted_channels": {"RANDOM": [8, 16, 256]}, "min_channel_skip": 1, "max_channel_skip": {"RANDOM": [1, 2, 9]}}, "conditional_frequency": 0.06776013062193854, "overall_frequency": 0.032782764811490124, "count": 913}]}, "shattered_channel": {"count": 3530, "frequency": 0.0238874153784845, "categories_count": 5, "domain_classes": [{"in_range": [100.0, 100.0], "count": 3450, "frequency": 0.9773371104815864}, {"random": [100.0, 100.0], "count": 80, "values": {"in_range": 0.9996681492033558, "zero": 0.0001335497108446412, "flip": 0.0001902071639302466, "out_of_range": 8.093921869372196e-06}, "frequency": 0.0226628895184136}], "parameters": [{"keys": {"avg_span_corruption_pct": [90.0, 100.0], "affected_channels_pct": [0.0, 10.0]}, "stats": {"max_corrupted_channels": 8, "min_channel_skip": 1, "max_channel_skip": 3, "min_span_width": 2, "max_span_width": 34}, "conditional_frequency": 0.3039660056657224, "overall_frequency": 0.0385278276481149, "count": 1073}, {"keys": {"avg_span_corruption_pct": [30.0, 40.0], "affected_channels_pct": [0.0, 10.0]}, "stats": {"max_corrupted_channels": 8, "min_channel_skip": 1, "max_channel_skip": 3, "min_span_width": 6, "max_span_width": 64}, "conditional_frequency": 0.2405099150141643, "overall_frequency": 0.030484739676840216, "count": 849}, {"keys": {"avg_span_corruption_pct": [50.0, 60.0], "affected_channels_pct": [0.0, 10.0]}, "stats": {"max_corrupted_channels": 8, "min_channel_skip": 1, "max_channel_skip": 3, "min_span_width": 4, "max_span_width": 64}, "conditional_frequency": 0.1643059490084986, "overall_frequency": 0.02082585278276481, "count": 580}, {"keys": {"avg_span_corruption_pct": [40.0, 50.0], "affected_channels_pct": [0.0, 10.0]}, "stats": {"max_corrupted_channels": 8, "min_channel_skip": 1, "max_channel_skip": 3, "min_span_width": 4, "max_span_width": 64}, "conditional_frequency": 0.11671388101983003, "overall_frequency": 0.014793536804308798, "count": 412}, {"keys": {"avg_span_corruption_pct": {"RANDOM": [[20.0, 30.0], [0.0, 10.0], [70.0, 80.0], [10.0, 20.0], [80.0, 90.0], [60.0, 70.0]]}, "affected_channels_pct": [0.0, 10.0]}, "stats": {"max_corrupted_channels": 8, "min_channel_skip": 1, "max_channel_skip": {"RANDOM": [2, 3]}, "min_span_width": {"RANDOM": [3, 4, 8, 12, 26]}, "max_span_width": {"RANDOM": [64, 57, 40, 45]}}, "conditional_frequency": 0.1745042492917847, "overall_frequency": 0.022118491921005387, "count": 616}]}, "single": {"count": 5406, "frequency": 0.686772950389426, "categories_count": 1, "domain_classes": [{"in_range": [100.0, 100.0], "count": 4572, "frequency": 0.8457269700332963}, {"out_of_range": [100.0, 100.0], "count": 833, "frequency": 0.1540880503144654}, {"random": [100.0, 100.0], "count": 1, "values": {"in_range": 0.8457269700332963, "out_of_range": 0.1540880503144654, "zero": 0.0001849796522382538}, "frequency": 0.0001849796522382538}], "parameters": [{"keys": {}, "stats": {}, "conditional_frequency": 1.0, "overall_frequency": 0.19411131059245962, "count": 5406}]}, "single_block": {"count": 385, "frequency": 0.0658544034392974, "categories_count": 1, "domain_classes": [{"in_range": [100.0, 100.0], "count": 380, "frequency": 0.987012987012987}, {"random": [100.0, 100.0], "count": 5, "values": {"in_range": 0.9996336727965419, "out_of_range": 7.326544069162575e-05, "flip": 0.0001465308813832515, "zero": 0.0001465308813832515}, "frequency": 0.012987012987012988}], "parameters": [{"keys": {"block_size": {"RANDOM": [64, 16, 32]}, "block_corruption_pct": {"RANDOM": [[70.0, 80.0], [90.0, 100.0], [80.0, 90.0], [50.0, 60.0], [60.0, 70.0]]}}, "stats": {}, "conditional_frequency": 1.0, "overall_frequency": 0.013824057450628367, "count": 385}]}, "single_channel_random": {"count": 864, "frequency": 0.1671777092122737, "categories_count": 1, "domain_classes": [{"in_range": [100.0, 100.0], "count": 862, "frequency": 0.9976851851851852}, {"random": [100.0, 100.0], "count": 2, "values": {"in_range": 0.9998463075386153, "zero": 7.684623069238454e-05, "flip": 7.684623069238454e-05}, "frequency": 0.0023148148148148147}], "parameters": [{"keys": {"channel_corruption_pct": {"RANDOM": [[20.0, 30.0], [0.0, 10.0], [10.0, 20.0], [40.0, 50.0], [30.0, 40.0]]}}, "stats": {"max_cardinality": {"RANDOM": [32, 6, 12, 19, 25]}, "min_value_skip": 1, "max_value_skip": {"RANDOM": [36, 39, 42, 43, 18]}}, "conditional_frequency": 1.0, "overall_frequency": 0.031023339317773787, "count": 864}]}, "skip_4": {"count": 412, "frequency": 0.014793536804308798, "categories_count": 1, "domain_classes": [{"in_range": [100.0, 100.0], "count": 410, "frequency": 0.9951456310679612}, {"random": [100.0, 100.0], "count": 2, "values": {"in_range": 0.9998951891835237, "zero": 5.2405408238130174e-05, "flip": 5.2405408238130174e-05}, "frequency": 0.0048543689320388345}], "parameters": [{"keys": {"skip_amount": 4, "unique_channel_indexes": {"RANDOM": [2, 3, 4, 5, 6, 7, 8]}, "indexes_corruption_pct": [90.0, 100.0], "affected_channels_pct": [0.0, 10.0]}, "stats": {"max_corrupted_channels": 8, "min_channel_skip": 1, "max_channel_skip": {"RANDOM": [1, 2]}}, "conditional_frequency": 1.0, "overall_frequency": 0.014793536804308798, "count": 412}]}, "same_row": {"count": 94, "frequency": 3.6649259601564495e-06, "categories_count": 1, "domain_classes": [{"random": [100.0, 100.0], "count": 94, "values": {"in_range": 1.0}, "frequency": 1.0}], "parameters": [{"keys": {"row_corruption_pct": {"RANDOM": [[70.0, 80.0], [90.0, 100.0], [80.0, 90.0], [50.0, 60.0], [60.0, 70.0], [40.0, 50.0]]}}, "stats": {"max_cardinality": {"RANDOM": [8, 3, 4, 5]}, "min_value_skip": 1, "max_value_skip": {"RANDOM": [2, 3, 4, 5]}}, "conditional_frequency": 1.0, "overall_frequency": 0.0033752244165170557, "count": 94}]}, "bullet_wake": {"count": 1278, "frequency": 0.000713551156502, "categories_count": 1, "domain_classes": [{"in_range": [100.0, 100.0], "count": 1269, "frequency": 0.9929577464788732}, {"random": [100.0, 100.0], "count": 9, "values": {"in_range": 0.9990737882062365, "flip": 0.00030873726458783575, "zero": 0.0006174745291756715}, "frequency": 0.007042253521126761}], "parameters": [{"keys": {"affected_channels_pct": [0.0, 10.0]}, "stats": {"max_corrupted_channels": 8, "min_channel_skip": 1, "max_channel_skip": 4}, "conditional_frequency": 1.0, "overall_frequency": 0.045888689407540394, "count": 1278}]}, "quasi_shattered_channel": {"count": 409, "frequency": 0.0071829504556128, "categories_count": 1, "domain_classes": [{"in_range": [100.0, 100.0], "count": 402, "frequency": 0.9828850855745721}, {"random": [100.0, 100.0], "count": 7, "values": {"in_range": 0.999387737251815, "flip": 0.0005247966413014956, "zero": 8.746610688358261e-05}, "frequency": 0.017114914425427872}], "parameters": [{"keys": {"avg_span_corruption_pct": {"RANDOM": [[20.0, 30.0], [90.0, 100.0], [10.0, 20.0], [80.0, 90.0], [50.0, 60.0], [40.0, 50.0], [30.0, 40.0]]}, "affected_channels_pct": [0.0, 10.0]}, "stats": {"max_corrupted_channels": 8, "min_channel_skip": 1, "max_channel_skip": {"RANDOM": [1, 2, 3]}, "min_span_width": {"RANDOM": [1, 2]}, "max_span_width": {"RANDOM": [3, 6, 10, 18, 56]}}, "conditional_frequency": 1.0, "overall_frequency": 0.014685816876122082, "count": 409}]}, "rectangles": {"count": 1998, "frequency": 0.0324386356053544, "categories_count": 1, "domain_classes": [{"in_range": [100.0, 100.0], "count": 1961, "frequency": 0.9814814814814815}, {"random": [100.0, 100.0], "count": 37, "values": {"in_range": 0.9991034442682694, "out_of_range": 0.0006060052631142029, "flip": 0.0002241389329326504, "zero": 6.641153568374827e-05}, "frequency": 0.018518518518518517}], "parameters": [{"keys": {"rectangle_width": 2, "rectangle_height": 2, "affected_channels_pct": [0.0, 10.0]}, "stats": {"max_corrupted_channels": 8, "min_channel_skip": 1, "max_channel_skip": 2}, "conditional_frequency": 1.0, "overall_frequency": 0.07174147217235188, "count": 1998}]}}