{"_rejected_tensors_proportion": 0.0, "_rejected_tensor_count": 19586, "_tensor_count": 19586, "_categories_count": 6, "single": {"count": 2868, "frequency": 0.517787993869657, "categories_count": 1, "domain_classes": [{"in_range": [100.0, 100.0], "count": 2651, "frequency": 0.9243375174337517}, {"out_of_range": [100.0, 100.0], "count": 217, "frequency": 0.07566248256624826}], "parameters": [{"keys": {}, "stats": {}, "conditional_frequency": 1.0, "overall_frequency": 0.1464311242724395, "count": 2868}]}, "single_block": {"count": 2328, "frequency": 0.0059484597631143, "categories_count": 6, "domain_classes": [{"in_range": [100.0, 100.0], "count": 2307, "frequency": 0.990979381443299}, {"random": [100.0, 100.0], "count": 21, "values": {"in_range": 0.9898057964715412, "out_of_range": 0.010194203528458819}, "frequency": 0.00902061855670103}], "parameters": [{"keys": {"block_size": 64, "block_corruption_pct": [90.0, 100.0]}, "stats": {}, "conditional_frequency": 0.311426116838488, "overall_frequency": 0.03701623608700092, "count": 725}, {"keys": {"block_size": 64, "block_corruption_pct": [60.0, 70.0]}, "stats": {}, "conditional_frequency": 0.10395189003436427, "overall_frequency": 0.0123557643214541, "count": 242}, {"keys": {"block_size": 64, "block_corruption_pct": [70.0, 80.0]}, "stats": {}, "conditional_frequency": 0.10352233676975946, "overall_frequency": 0.012304707444092719, "count": 241}, {"keys": {"block_size": 64, "block_corruption_pct": [50.0, 60.0]}, "stats": {}, "conditional_frequency": 0.0975085910652921, "overall_frequency": 0.011589911161033391, "count": 227}, {"keys": {"block_size": 64, "block_corruption_pct": [80.0, 90.0]}, "stats": {}, "conditional_frequency": 0.09321305841924399, "overall_frequency": 0.011079342387419585, "count": 217}, {"keys": {"block_size": {"RANDOM": [32, 16]}, "block_corruption_pct": {"RANDOM": [[70.0, 80.0], [90.0, 100.0], [80.0, 90.0], [50.0, 60.0], [60.0, 70.0]]}}, "stats": {}, "conditional_frequency": 0.29037800687285226, "overall_frequency": 0.03451444909629327, "count": 676}]}, "same_row": {"count": 279, "frequency": 3.2339217693530736e-06, "categories_count": 2, "domain_classes": [{"in_range": [100.0, 100.0], "count": 279, "frequency": 1.0}], "parameters": [{"keys": {"row_corruption_pct": [90.0, 100.0]}, "stats": {"max_cardinality": 8, "min_value_skip": 1, "max_value_skip": 2}, "conditional_frequency": 0.9605734767025089, "overall_frequency": 0.013683243132849994, "count": 268}, {"keys": {"row_corruption_pct": {"RANDOM": [[80.0, 90.0], [60.0, 70.0], [40.0, 50.0], [70.0, 80.0]]}}, "stats": {"max_cardinality": {"RANDOM": [2, 3, 4, 5]}, "min_value_skip": {"RANDOM": [1, 3]}, "max_value_skip": 3}, "conditional_frequency": 0.03942652329749104, "overall_frequency": 0.0005616256509751864, "count": 11}]}, "bullet_wake": {"count": 4124, "frequency": 0.1556073136489822, "categories_count": 1, "domain_classes": [{"in_range": [100.0, 100.0], "count": 3886, "frequency": 0.9422890397672163}, {"random": [100.0, 100.0], "count": 238, "values": {"out_of_range": 0.04447039199332777, "in_range": 0.9548957464553794, "flip": 3.336113427856547e-05, "zero": 0.0006005004170141785}, "frequency": 0.05771096023278371}], "parameters": [{"keys": {"affected_channels_pct": [0.0, 10.0]}, "stats": {"max_corrupted_channels": 8, "min_channel_skip": 1, "max_channel_skip": 7}, "conditional_frequency": 1.0, "overall_frequency": 0.2105585622383335, "count": 4124}]}, "single_channel_random": {"count": 468, "frequency": 0.0019818739198723, "categories_count": 1, "domain_classes": [{"in_range": [100.0, 100.0], "count": 468, "frequency": 1.0}], "parameters": [{"keys": {"channel_corruption_pct": {"RANDOM": [[20.0, 30.0], [0.0, 10.0], [10.0, 20.0], [40.0, 50.0], [30.0, 40.0]]}}, "stats": {"max_cardinality": {"RANDOM": [32, 6, 12, 19, 25]}, "min_value_skip": 1, "max_value_skip": {"RANDOM": [26, 50, 43, 13]}}, "conditional_frequency": 1.0, "overall_frequency": 0.023894618605126112, "count": 468}]}, "skip_4": {"count": 13, "frequency": 0.0006637394056979476, "categories_count": 1, "domain_classes": [{"random": [100.0, 100.0], "count": 13, "values": {"in_range": 1.0}, "frequency": 1.0}], "parameters": [{"keys": {"skip_amount": 4, "unique_channel_indexes": {"RANDOM": [2, 3, 5]}, "indexes_corruption_pct": [90.0, 100.0], "affected_channels_pct": [0.0, 10.0]}, "stats": {"max_corrupted_channels": 1, "min_channel_skip": 1, "max_channel_skip": 1}, "conditional_frequency": 1.0, "overall_frequency": 0.0006637394056979476, "count": 13}]}, "multi_channel_block": {"count": 8347, "frequency": 0.3186676204528448, "categories_count": 6, "domain_classes": [{"in_range": [100.0, 100.0], "count": 7007, "frequency": 0.8394632802204385}, {"out_of_range": [100.0, 100.0], "count": 832, "frequency": 0.0996765304899964}, {"random": [100.0, 100.0], "count": 508, "values": {"in_range": 0.7984230328172828, "out_of_range": 0.10293854534437868, "zero": 0.09863842183833853}, "frequency": 0.06086018928956511}], "parameters": [{"keys": {"block_size": 64, "avg_block_corruption_pct": [90.0, 100.0], "affected_channels_pct": [0.0, 10.0]}, "stats": {"max_corrupted_channels": 8, "min_channel_skip": 1, "max_channel_skip": 1}, "conditional_frequency": 0.6456211812627292, "overall_frequency": 0.27514551210047994, "count": 5389}, {"keys": {"block_size": 64, "avg_block_corruption_pct": [80.0, 90.0], "affected_channels_pct": [0.0, 10.0]}, "stats": {"max_corrupted_channels": 8, "min_channel_skip": 1, "max_channel_skip": 1}, "conditional_frequency": 0.0763148436564035, "overall_frequency": 0.03252323087919943, "count": 637}, {"keys": {"block_size": 64, "avg_block_corruption_pct": [70.0, 80.0], "affected_channels_pct": [0.0, 10.0]}, "stats": {"max_corrupted_channels": 8, "min_channel_skip": 1, "max_channel_skip": 1}, "conditional_frequency": 0.06349586677848329, "overall_frequency": 0.027060145001531706, "count": 530}, {"keys": {"block_size": 64, "avg_block_corruption_pct": [60.0, 70.0], "affected_channels_pct": [0.0, 10.0]}, "stats": {"max_corrupted_channels": 8, "min_channel_skip": 1, "max_channel_skip": 1}, "conditional_frequency": 0.045645141967173834, "overall_frequency": 0.019452670274686, "count": 381}, {"keys": {"block_size": 64, "avg_block_corruption_pct": [50.0, 60.0], "affected_channels_pct": [0.0, 10.0]}, "stats": {"max_corrupted_channels": 8, "min_channel_skip": 1, "max_channel_skip": 1}, "conditional_frequency": 0.042530250389361444, "overall_frequency": 0.018125191463290106, "count": 355}, {"keys": {"block_size": {"RANDOM": [32, 16, 64]}, "avg_block_corruption_pct": {"RANDOM": [[70.0, 80.0], [90.0, 100.0], [80.0, 90.0], [50.0, 60.0], [60.0, 70.0], [40.0, 50.0]]}, "affected_channels_pct": {"RANDOM": [[0.0, 10.0], [90.0, 100.0]]}}, "stats": {"max_corrupted_channels": {"RANDOM": [8, 144]}, "min_channel_skip": 1, "max_channel_skip": 1}, "conditional_frequency": 0.1263927159458488, "overall_frequency": 0.05386500561625651, "count": 1055}]}, "shattered_channel": {"count": 1159, "frequency": 3.2680075858835347e-06, "categories_count": 2, "domain_classes": [{"in_range": [100.0, 100.0], "count": 1132, "frequency": 0.9767040552200172}, {"random": [100.0, 100.0], "count": 27, "values": {"in_range": 0.9919558458360286, "out_of_range": 0.006426976608309163, "zero": 0.0016171775556622081}, "frequency": 0.023295944779982744}], "parameters": [{"keys": {"avg_span_corruption_pct": [90.0, 100.0], "affected_channels_pct": [0.0, 10.0]}, "stats": {"max_corrupted_channels": 8, "min_channel_skip": 1, "max_channel_skip": 1, "min_span_width": 2, "max_span_width": 10}, "conditional_frequency": 0.6039689387402933, "overall_frequency": 0.035739814152966405, "count": 700}, {"keys": {"avg_span_corruption_pct": {"RANDOM": [[20.0, 30.0], [0.0, 10.0], [10.0, 20.0], [40.0, 50.0], [30.0, 40.0]]}, "affected_channels_pct": [0.0, 10.0]}, "stats": {"max_corrupted_channels": 8, "min_channel_skip": 1, "max_channel_skip": 1, "min_span_width": 64, "max_span_width": 64}, "conditional_frequency": 0.39603106125970666, "overall_frequency": 0.023435106708873686, "count": 459}]}}