{"_rejected_tensors_proportion": 0.0, "_rejected_tensor_count": 12124, "_tensor_count": 12124, "_categories_count": 3, "full_channels": {"count": 9456, "frequency": 0.757430524533685, "categories_count": 3, "domain_classes": [{"in_range": [100.0, 100.0], "count": 8378, "frequency": 0.8859983079526227}, {"flip": [87.5, 100.0], "in_range": [0.0, 100], "count": 393, "frequency": 0.041560913705583756}, {"in_range": [62.5, 75.0], "out_of_range": [25.0, 100], "count": 175, "frequency": 0.018506768189509307}, {"random": [100.0, 100.0], "count": 510, "values": {"in_range": 0.5933578308395955, "out_of_range": 0.010490230483443882, "flip": 0.04991922783550901, "zero": 0.34623271084145163}, "frequency": 0.053934010152284266}], "parameters": [{"keys": {"avg_channel_corruption_pct": [90.0, 100.0], "affected_channels_pct": [0.0, 10.0]}, "stats": {"max_corrupted_channels": 8, "min_channel_skip": 1, "max_channel_skip": 1}, "conditional_frequency": 0.9325296108291032, "overall_frequency": 0.7273177169251073, "count": 8818}, {"keys": {"avg_channel_corruption_pct": [70.0, 80.0], "affected_channels_pct": [0.0, 10.0]}, "stats": {"max_corrupted_channels": 8, "min_channel_skip": 1, "max_channel_skip": 1}, "conditional_frequency": 0.06133671742808799, "overall_frequency": 0.04783899703068294, "count": 580}, {"keys": {"avg_channel_corruption_pct": {"RANDOM": [[80.0, 90.0], [90.0, 100.0]]}, "affected_channels_pct": {"RANDOM": [[0.0, 10.0], [90.0, 100.0]]}}, "stats": {"max_corrupted_channels": {"RANDOM": [576, 2]}, "min_channel_skip": 1, "max_channel_skip": 1}, "conditional_frequency": 0.006133671742808798, "overall_frequency": 0.004783899703068294, "count": 58}]}, "same_row": {"count": 152, "frequency": 9.833765274137056e-05, "categories_count": 1, "domain_classes": [{"in_range": [100.0, 100.0], "count": 152, "frequency": 1.0}], "parameters": [{"keys": {"row_corruption_pct": [90.0, 100.0]}, "stats": {"max_cardinality": 2, "min_value_skip": 1, "max_value_skip": 1}, "conditional_frequency": 1.0, "overall_frequency": 0.012537116463213462, "count": 152}]}, "shattered_channel": {"count": 1092, "frequency": 0.0968992874060284, "categories_count": 3, "domain_classes": [{"in_range": [100.0, 100.0], "count": 939, "frequency": 0.8598901098901099}, {"zero": [100.0, 100.0], "count": 135, "frequency": 0.12362637362637363}, {"random": [100.0, 100.0], "count": 18, "values": {"in_range": 0.48927707776505025, "out_of_range": 0.0007000127275041364, "zero": 0.5052182766959399, "flip": 0.0048046328115056635}, "frequency": 0.016483516483516484}], "parameters": [{"keys": {"avg_span_corruption_pct": [90.0, 100.0], "affected_channels_pct": [0.0, 10.0]}, "stats": {"max_corrupted_channels": 8, "min_channel_skip": 1, "max_channel_skip": 1, "min_span_width": 2, "max_span_width": 4}, "conditional_frequency": 0.6694139194139194, "overall_frequency": 0.060293632464533155, "count": 731}, {"keys": {"avg_span_corruption_pct": [60.0, 70.0], "affected_channels_pct": [0.0, 10.0]}, "stats": {"max_corrupted_channels": 8, "min_channel_skip": 1, "max_channel_skip": 1, "min_span_width": 3, "max_span_width": 3}, "conditional_frequency": 0.20604395604395603, "overall_frequency": 0.018558231606730452, "count": 225}, {"keys": {"avg_span_corruption_pct": {"RANDOM": [[70.0, 80.0], [90.0, 100.0], [80.0, 90.0], [50.0, 60.0], [40.0, 50.0]]}, "affected_channels_pct": {"RANDOM": [[0.0, 10.0], [90.0, 100.0]]}}, "stats": {"max_corrupted_channels": {"RANDOM": [8, 576]}, "min_channel_skip": 1, "max_channel_skip": {"RANDOM": [1, 2]}, "min_span_width": {"RANDOM": [3, 4]}, "max_span_width": 4}, "conditional_frequency": 0.12454212454212454, "overall_frequency": 0.011217419993401518, "count": 136}]}, "single": {"count": 248, "frequency": 0.0002227903915923, "categories_count": 1, "domain_classes": [{"in_range": [100.0, 100.0], "count": 245, "frequency": 0.9879032258064516}, {"random": [100.0, 100.0], "count": 3, "values": {"in_range": 0.9879032258064516, "flip": 0.012096774193548387}, "frequency": 0.012096774193548387}], "parameters": [{"keys": {}, "stats": {}, "conditional_frequency": 1.0, "overall_frequency": 0.02045529528208512, "count": 248}]}, "bullet_wake": {"count": 1121, "frequency": 0.1453257695459612, "categories_count": 1, "domain_classes": [{"in_range": [100.0, 100.0], "count": 1082, "frequency": 0.9652096342551294}, {"random": [100.0, 100.0], "count": 39, "values": {"out_of_range": 0.007341622261693309, "in_range": 0.9824748371817643, "flip": 0.010183540556542333}, "frequency": 0.03479036574487065}], "parameters": [{"keys": {"affected_channels_pct": [0.0, 10.0]}, "stats": {"max_corrupted_channels": 8, "min_channel_skip": 1, "max_channel_skip": 5}, "conditional_frequency": 1.0, "overall_frequency": 0.09246123391619927, "count": 1121}]}, "single_channel_random": {"count": 55, "frequency": 2.323273162441621e-05, "categories_count": 1, "domain_classes": [{"random": [100.0, 100.0], "count": 55, "values": {"in_range": 1.0}, "frequency": 1.0}], "parameters": [{"keys": {"channel_corruption_pct": [40.0, 50.0]}, "stats": {"max_cardinality": 2, "min_value_skip": 1, "max_value_skip": 3}, "conditional_frequency": 1.0, "overall_frequency": 0.0045364566149785545, "count": 55}]}}